{
    "id": "openstack%2Fglance~master~I3365d028ab67931517d2f94cc4b7e3752fbdb869",
    "project": "openstack/glance",
    "branch": "master",
    "topic": "bug/1037592",
    "hashtags": [],
    "change_id": "I3365d028ab67931517d2f94cc4b7e3752fbdb869",
    "subject": "Remove unused imports",
    "status": "MERGED",
    "created": "2012-08-16 14:18:50.000000000",
    "updated": "2012-08-17 14:10:10.000000000",
    "submitted": "2012-08-17 14:10:10.000000000",
    "submitter": {
        "_account_id": 3,
        "name": "Jenkins",
        "username": "jenkins"
    },
    "insertions": 0,
    "deletions": 10,
    "total_comment_count": 0,
    "unresolved_comment_count": 0,
    "has_review_started": true,
    "meta_rev_id": "a4fd591ab1eccab3aca9f3bdf13861ac4227baf8",
    "_number": 11464,
    "owner": {
        "_account_id": 2481,
        "name": "Rongze Zhu",
        "email": "zrzhit@gmail.com",
        "username": "zrzhit"
    },
    "labels": {
        "Verified": {
            "approved": {
                "_account_id": 3,
                "name": "Jenkins",
                "username": "jenkins"
            },
            "recommended": {
                "_account_id": 2166,
                "name": "SmokeStack CI",
                "username": "smokestack",
                "tags": [
                    "SERVICE_USER"
                ]
            },
            "all": [
                {
                    "value": 0,
                    "_account_id": 1132,
                    "name": "Brian Waldon",
                    "email": "brian@waldon.cc",
                    "username": "bcwaldon"
                },
                {
                    "value": 1,
                    "date": "2012-08-17 02:30:37.000000000",
                    "_account_id": 2166,
                    "name": "SmokeStack CI",
                    "username": "smokestack",
                    "tags": [
                        "SERVICE_USER"
                    ]
                },
                {
                    "value": 0,
                    "_account_id": 2481,
                    "name": "Rongze Zhu",
                    "email": "zrzhit@gmail.com",
                    "username": "zrzhit"
                },
                {
                    "value": 0,
                    "_account_id": 706,
                    "name": "Brian Lamar",
                    "email": "brian.lamar@rackspace.com",
                    "username": "blamar"
                },
                {
                    "value": 2,
                    "date": "2012-08-17 14:10:10.000000000",
                    "_account_id": 3,
                    "name": "Jenkins",
                    "username": "jenkins"
                }
            ],
            "values": {
                "-2": "Fails",
                "-1": "Doesn't seem to work",
                " 0": "No score",
                "+1": "Works for me",
                "+2": "Verified"
            },
            "description": "",
            "value": 1,
            "default_value": 0,
            "optional": true
        },
        "Code-Review": {
            "approved": {
                "_account_id": 1132,
                "name": "Brian Waldon",
                "email": "brian@waldon.cc",
                "username": "bcwaldon"
            },
            "all": [
                {
                    "value": 2,
                    "date": "2012-08-17 14:10:10.000000000",
                    "post_submit": true,
                    "_account_id": 1132,
                    "name": "Brian Waldon",
                    "email": "brian@waldon.cc",
                    "username": "bcwaldon"
                },
                {
                    "value": 0,
                    "_account_id": 2166,
                    "name": "SmokeStack CI",
                    "username": "smokestack",
                    "tags": [
                        "SERVICE_USER"
                    ]
                },
                {
                    "value": 0,
                    "_account_id": 2481,
                    "name": "Rongze Zhu",
                    "email": "zrzhit@gmail.com",
                    "username": "zrzhit"
                },
                {
                    "value": 2,
                    "date": "2012-08-17 13:55:13.000000000",
                    "_account_id": 706,
                    "name": "Brian Lamar",
                    "email": "brian.lamar@rackspace.com",
                    "username": "blamar"
                },
                {
                    "value": 0,
                    "_account_id": 3,
                    "name": "Jenkins",
                    "username": "jenkins"
                }
            ],
            "values": {
                "-2": "Do not merge",
                "-1": "This patch needs further work before it can be merged",
                " 0": "No score",
                "+1": "Looks good to me, but someone else must approve",
                "+2": "Looks good to me (core reviewer)"
            },
            "description": "",
            "default_value": 0,
            "optional": true
        },
        "Workflow": {
            "approved": {
                "_account_id": 706,
                "name": "Brian Lamar",
                "email": "brian.lamar@rackspace.com",
                "username": "blamar"
            },
            "all": [
                {
                    "value": 0,
                    "_account_id": 1132,
                    "name": "Brian Waldon",
                    "email": "brian@waldon.cc",
                    "username": "bcwaldon"
                },
                {
                    "value": 0,
                    "_account_id": 2166,
                    "name": "SmokeStack CI",
                    "username": "smokestack",
                    "tags": [
                        "SERVICE_USER"
                    ]
                },
                {
                    "value": 0,
                    "_account_id": 2481,
                    "name": "Rongze Zhu",
                    "email": "zrzhit@gmail.com",
                    "username": "zrzhit"
                },
                {
                    "value": 1,
                    "date": "2012-08-17 13:55:13.000000000",
                    "_account_id": 706,
                    "name": "Brian Lamar",
                    "email": "brian.lamar@rackspace.com",
                    "username": "blamar"
                },
                {
                    "value": 0,
                    "_account_id": 3,
                    "name": "Jenkins",
                    "username": "jenkins"
                }
            ],
            "values": {
                "-1": "Work in progress",
                " 0": "Ready for reviews",
                "+1": "Approved"
            },
            "description": "",
            "default_value": 0,
            "optional": true
        },
        "Review-Priority": {
            "all": [
                {
                    "value": 0,
                    "_account_id": 1132,
                    "name": "Brian Waldon",
                    "email": "brian@waldon.cc",
                    "username": "bcwaldon"
                },
                {
                    "value": 0,
                    "_account_id": 2166,
                    "name": "SmokeStack CI",
                    "username": "smokestack",
                    "tags": [
                        "SERVICE_USER"
                    ]
                },
                {
                    "value": 0,
                    "_account_id": 2481,
                    "name": "Rongze Zhu",
                    "email": "zrzhit@gmail.com",
                    "username": "zrzhit"
                },
                {
                    "value": 0,
                    "_account_id": 706,
                    "name": "Brian Lamar",
                    "email": "brian.lamar@rackspace.com",
                    "username": "blamar"
                },
                {
                    "value": 0,
                    "_account_id": 3,
                    "name": "Jenkins",
                    "username": "jenkins"
                }
            ],
            "values": {
                "-1": "Branch Freeze",
                " 0": "No Priority",
                "+1": "Important Change",
                "+2": "Top Priority / Holds Gate"
            },
            "description": "",
            "default_value": 0,
            "optional": true
        }
    },
    "removable_reviewers": [],
    "reviewers": {
        "REVIEWER": [
            {
                "_account_id": 3,
                "name": "Jenkins",
                "username": "jenkins"
            },
            {
                "_account_id": 706,
                "name": "Brian Lamar",
                "email": "brian.lamar@rackspace.com",
                "username": "blamar"
            },
            {
                "_account_id": 1132,
                "name": "Brian Waldon",
                "email": "brian@waldon.cc",
                "username": "bcwaldon"
            },
            {
                "_account_id": 2166,
                "name": "SmokeStack CI",
                "username": "smokestack",
                "tags": [
                    "SERVICE_USER"
                ]
            },
            {
                "_account_id": 2481,
                "name": "Rongze Zhu",
                "email": "zrzhit@gmail.com",
                "username": "zrzhit"
            }
        ]
    },
    "pending_reviewers": {},
    "reviewer_updates": [
        {
            "updated": "2012-08-16 20:19:06.000000000",
            "updated_by": {
                "_account_id": 1132,
                "name": "Brian Waldon",
                "email": "brian@waldon.cc",
                "username": "bcwaldon"
            },
            "reviewer": {
                "_account_id": 1132,
                "name": "Brian Waldon",
                "email": "brian@waldon.cc",
                "username": "bcwaldon"
            },
            "state": "REVIEWER"
        },
        {
            "updated": "2012-08-17 02:30:37.000000000",
            "updated_by": {
                "_account_id": 2166,
                "name": "SmokeStack CI",
                "username": "smokestack",
                "tags": [
                    "SERVICE_USER"
                ]
            },
            "reviewer": {
                "_account_id": 2166,
                "name": "SmokeStack CI",
                "username": "smokestack",
                "tags": [
                    "SERVICE_USER"
                ]
            },
            "state": "REVIEWER"
        },
        {
            "updated": "2012-08-17 13:55:13.000000000",
            "updated_by": {
                "_account_id": 706,
                "name": "Brian Lamar",
                "email": "brian.lamar@rackspace.com",
                "username": "blamar"
            },
            "reviewer": {
                "_account_id": 706,
                "name": "Brian Lamar",
                "email": "brian.lamar@rackspace.com",
                "username": "blamar"
            },
            "state": "REVIEWER"
        },
        {
            "updated": "2012-08-17 14:10:10.000000000",
            "updated_by": {
                "_account_id": 3,
                "name": "Jenkins",
                "username": "jenkins"
            },
            "reviewer": {
                "_account_id": 3,
                "name": "Jenkins",
                "username": "jenkins"
            },
            "state": "REVIEWER"
        }
    ],
    "messages": [
        {
            "id": "e3737c929bf1bb5ba9ee1aa7c792c6904b610a72",
            "author": {
                "_account_id": 3,
                "name": "Jenkins",
                "username": "jenkins"
            },
            "real_author": {
                "_account_id": 3,
                "name": "Jenkins",
                "username": "jenkins"
            },
            "date": "2012-08-16 14:28:31.000000000",
            "message": "Patch Set 1: Doesn't seem to work\n\nBuild failed\n\n- https://jenkins.openstack.org/job/gate-glance-merge/1797/consoleFull : SUCCESS\n- https://jenkins.openstack.org/job/gate-glance-pep8/1909/consoleFull : SUCCESS\n- https://jenkins.openstack.org/job/gate-glance-python26/1416/consoleFull : FAILURE\n- https://jenkins.openstack.org/job/gate-glance-python27/1420/consoleFull : SUCCESS\n- https://jenkins.openstack.org/job/gate-tempest-devstack-vm/8140/consoleFull : SUCCESS\n",
            "accounts_in_message": [],
            "_revision_number": 1
        },
        {
            "id": "7c196b79039d5435a48e519dacdc1cd757f1cc56",
            "author": {
                "_account_id": 2166,
                "name": "SmokeStack CI",
                "username": "smokestack",
                "tags": [
                    "SERVICE_USER"
                ]
            },
            "real_author": {
                "_account_id": 2166,
                "name": "SmokeStack CI",
                "username": "smokestack",
                "tags": [
                    "SERVICE_USER"
                ]
            },
            "date": "2012-08-16 14:41:08.000000000",
            "message": "Patch Set 1: Works for me\n\nSmokeStack Results (patch set 1):\n\tUnit Success: http://smokestack.openstack.org/?go=/jobs/30020\n\tLibvirt (Fedora 17) Success: http://smokestack.openstack.org/?go=/jobs/30018\n\tXenServer 5.6 (F17 domU) Success: http://smokestack.openstack.org/?go=/jobs/30019\n",
            "accounts_in_message": [],
            "_revision_number": 1
        },
        {
            "id": "3cb40f24f98d926e7854c6569d96549ca3f85a50",
            "author": {
                "_account_id": 2481,
                "name": "Rongze Zhu",
                "email": "zrzhit@gmail.com",
                "username": "zrzhit"
            },
            "real_author": {
                "_account_id": 2481,
                "name": "Rongze Zhu",
                "email": "zrzhit@gmail.com",
                "username": "zrzhit"
            },
            "date": "2012-08-16 15:05:35.000000000",
            "message": "Patch Set 1:\n\nEnsure an interrupt signal does not cause a respawn storm test is ok in my computer. Why the Jenkins is FAIL?",
            "accounts_in_message": [],
            "_revision_number": 1
        },
        {
            "id": "5763a6c581d50afce201b62f6907cd8b5f3b3f60",
            "author": {
                "_account_id": 1132,
                "name": "Brian Waldon",
                "email": "brian@waldon.cc",
                "username": "bcwaldon"
            },
            "real_author": {
                "_account_id": 1132,
                "name": "Brian Waldon",
                "email": "brian@waldon.cc",
                "username": "bcwaldon"
            },
            "date": "2012-08-16 20:19:06.000000000",
            "message": "Patch Set 1: Looks good to me (core reviewer)\n\nJenkins is just being grumpy.",
            "accounts_in_message": [],
            "_revision_number": 1
        },
        {
            "id": "7b5f44985cb1e3fb25ae17306a60a8b3eb976afe",
            "author": {
                "_account_id": 2481,
                "name": "Rongze Zhu",
                "email": "zrzhit@gmail.com",
                "username": "zrzhit"
            },
            "real_author": {
                "_account_id": 2481,
                "name": "Rongze Zhu",
                "email": "zrzhit@gmail.com",
                "username": "zrzhit"
            },
            "date": "2012-08-17 01:29:34.000000000",
            "message": "Patch Set 1: Rebased",
            "accounts_in_message": [],
            "_revision_number": 1
        },
        {
            "id": "7985b4dbaf83c201bd6465b11379e9442a37bf58",
            "author": {
                "_account_id": 3,
                "name": "Jenkins",
                "username": "jenkins"
            },
            "real_author": {
                "_account_id": 3,
                "name": "Jenkins",
                "username": "jenkins"
            },
            "date": "2012-08-17 01:40:14.000000000",
            "message": "Patch Set 2: Works for me\n\nBuild successful\n\n- https://jenkins.openstack.org/job/gate-glance-merge/1809/consoleFull : SUCCESS\n- https://jenkins.openstack.org/job/gate-glance-pep8/1921/consoleFull : SUCCESS\n- https://jenkins.openstack.org/job/gate-glance-python26/1428/consoleFull : SUCCESS\n- https://jenkins.openstack.org/job/gate-glance-python27/1432/consoleFull : SUCCESS\n- https://jenkins.openstack.org/job/gate-tempest-devstack-vm/8271/consoleFull : SUCCESS\n",
            "accounts_in_message": [],
            "_revision_number": 2
        },
        {
            "id": "dab13db4aeee0e81cab4a50882967f4188e18922",
            "author": {
                "_account_id": 2166,
                "name": "SmokeStack CI",
                "username": "smokestack",
                "tags": [
                    "SERVICE_USER"
                ]
            },
            "real_author": {
                "_account_id": 2166,
                "name": "SmokeStack CI",
                "username": "smokestack",
                "tags": [
                    "SERVICE_USER"
                ]
            },
            "date": "2012-08-17 02:30:37.000000000",
            "message": "Patch Set 2: Works for me\n\nSmokeStack Results (patch set 2):\n\tUnit Success: http://smokestack.openstack.org/?go=/jobs/30206\n\tLibvirt (Fedora 17) Success: http://smokestack.openstack.org/?go=/jobs/30204\n\tXenServer 5.6 (F17 domU) Success: http://smokestack.openstack.org/?go=/jobs/30205\n",
            "accounts_in_message": [],
            "_revision_number": 2
        },
        {
            "id": "620831e54196f6a640cd59d66a6e0605ce097067",
            "author": {
                "_account_id": 3,
                "name": "Jenkins",
                "username": "jenkins"
            },
            "real_author": {
                "_account_id": 3,
                "name": "Jenkins",
                "username": "jenkins"
            },
            "date": "2012-08-17 13:55:13.000000000",
            "message": "Patch Set 2: No score\n\nStarting gate jobs.",
            "accounts_in_message": [],
            "_revision_number": 2
        },
        {
            "id": "1dc6951b4de2ad3b05fb5e7a13cecd8a7189b820",
            "author": {
                "_account_id": 706,
                "name": "Brian Lamar",
                "email": "brian.lamar@rackspace.com",
                "username": "blamar"
            },
            "real_author": {
                "_account_id": 706,
                "name": "Brian Lamar",
                "email": "brian.lamar@rackspace.com",
                "username": "blamar"
            },
            "date": "2012-08-17 13:55:13.000000000",
            "message": "Patch Set 2: Looks good to me (core reviewer); Approved\n\n",
            "accounts_in_message": [],
            "_revision_number": 2
        },
        {
            "id": "db54bac82dfd433377cdd78015f9f38f34c3b1c6",
            "author": {
                "_account_id": 3,
                "name": "Jenkins",
                "username": "jenkins"
            },
            "real_author": {
                "_account_id": 3,
                "name": "Jenkins",
                "username": "jenkins"
            },
            "date": "2012-08-17 14:10:10.000000000",
            "message": "Patch Set 2: Verified\n\nBuild successful\n\n- https://jenkins.openstack.org/job/gate-glance-merge/1811/consoleFull : SUCCESS\n- https://jenkins.openstack.org/job/gate-glance-pep8/1923/consoleFull : SUCCESS\n- https://jenkins.openstack.org/job/gate-glance-python26/1430/consoleFull : SUCCESS\n- https://jenkins.openstack.org/job/gate-glance-python27/1434/consoleFull : SUCCESS\n- https://jenkins.openstack.org/job/gate-tempest-devstack-vm/8320/consoleFull : SUCCESS\n",
            "accounts_in_message": [],
            "_revision_number": 2
        },
        {
            "id": "6021158ad7424122ed2215f68946a1a19ae0f066",
            "author": {
                "_account_id": 3,
                "name": "Jenkins",
                "username": "jenkins"
            },
            "real_author": {
                "_account_id": 3,
                "name": "Jenkins",
                "username": "jenkins"
            },
            "date": "2012-08-17 14:10:10.000000000",
            "message": "Change has been successfully merged into the git repository.",
            "accounts_in_message": [],
            "_revision_number": 2
        }
    ],
    "requirements": [],
    "submit_records": []
}