{
    "id": "openstack%2Fglance~master~If6775eb3ce85390bc5d579dff6c59c6066e77e9b",
    "project": "openstack/glance",
    "branch": "master",
    "topic": "bug/820643",
    "hashtags": [],
    "change_id": "If6775eb3ce85390bc5d579dff6c59c6066e77e9b",
    "subject": "Refactoring/cleanup around our exception handling",
    "status": "MERGED",
    "created": "2011-10-10 17:46:06.000000000",
    "updated": "2011-10-11 20:18:07.000000000",
    "submitted": "2011-10-11 20:18:07.000000000",
    "submitter": {
        "_account_id": 3,
        "name": "Jenkins",
        "username": "jenkins"
    },
    "insertions": 107,
    "deletions": 148,
    "total_comment_count": 2,
    "unresolved_comment_count": 0,
    "has_review_started": true,
    "meta_rev_id": "d0e2788d4455aad98583abc96c8c345412db6916",
    "_number": 825,
    "owner": {
        "_account_id": 7,
        "name": "Jay Pipes",
        "email": "jaypipes@gmail.com",
        "username": "jaypipes"
    },
    "labels": {
        "Verified": {
            "recommended": {
                "_account_id": 3,
                "name": "Jenkins",
                "username": "jenkins"
            },
            "all": [
                {
                    "value": 0,
                    "_account_id": 1132,
                    "name": "Brian Waldon",
                    "email": "brian@waldon.cc",
                    "username": "bcwaldon"
                },
                {
                    "value": 0,
                    "_account_id": 7,
                    "name": "Jay Pipes",
                    "email": "jaypipes@gmail.com",
                    "username": "jaypipes"
                },
                {
                    "value": 0,
                    "_account_id": 679,
                    "name": "Kevin L. Mitchell",
                    "email": "klmitch@mit.edu",
                    "username": "klmitch"
                },
                {
                    "value": 1,
                    "date": "2011-10-11 20:18:07.000000000",
                    "_account_id": 3,
                    "name": "Jenkins",
                    "username": "jenkins"
                }
            ],
            "values": {
                "-2": "Fails",
                "-1": "Doesn't seem to work",
                " 0": "No score",
                "+1": "Works for me",
                "+2": "Verified"
            },
            "description": "",
            "value": 1,
            "default_value": 0,
            "optional": true
        },
        "Code-Review": {
            "approved": {
                "_account_id": 1132,
                "name": "Brian Waldon",
                "email": "brian@waldon.cc",
                "username": "bcwaldon"
            },
            "all": [
                {
                    "value": 2,
                    "date": "2011-10-11 20:16:30.000000000",
                    "_account_id": 1132,
                    "name": "Brian Waldon",
                    "email": "brian@waldon.cc",
                    "username": "bcwaldon"
                },
                {
                    "value": 0,
                    "date": "2011-10-11 15:54:48.000000000",
                    "permitted_voting_range": {
                        "min": 0,
                        "max": 1
                    },
                    "_account_id": 7,
                    "name": "Jay Pipes",
                    "email": "jaypipes@gmail.com",
                    "username": "jaypipes"
                },
                {
                    "value": 1,
                    "date": "2011-10-11 16:02:59.000000000",
                    "permitted_voting_range": {
                        "min": 1,
                        "max": 1
                    },
                    "_account_id": 679,
                    "name": "Kevin L. Mitchell",
                    "email": "klmitch@mit.edu",
                    "username": "klmitch"
                },
                {
                    "value": 0,
                    "date": "2011-10-11 20:16:34.000000000",
                    "permitted_voting_range": {
                        "min": 0,
                        "max": 1
                    },
                    "_account_id": 3,
                    "name": "Jenkins",
                    "username": "jenkins"
                }
            ],
            "values": {
                "-2": "Do not merge",
                "-1": "This patch needs further work before it can be merged",
                " 0": "No score",
                "+1": "Looks good to me, but someone else must approve",
                "+2": "Looks good to me (core reviewer)"
            },
            "description": "",
            "default_value": 0,
            "optional": true
        },
        "Workflow": {
            "all": [
                {
                    "value": 0,
                    "_account_id": 1132,
                    "name": "Brian Waldon",
                    "email": "brian@waldon.cc",
                    "username": "bcwaldon"
                },
                {
                    "value": 0,
                    "_account_id": 7,
                    "name": "Jay Pipes",
                    "email": "jaypipes@gmail.com",
                    "username": "jaypipes"
                },
                {
                    "value": 0,
                    "_account_id": 679,
                    "name": "Kevin L. Mitchell",
                    "email": "klmitch@mit.edu",
                    "username": "klmitch"
                },
                {
                    "value": 0,
                    "_account_id": 3,
                    "name": "Jenkins",
                    "username": "jenkins"
                }
            ],
            "values": {
                "-1": "Work in progress",
                " 0": "Ready for reviews",
                "+1": "Approved"
            },
            "description": "",
            "default_value": 0,
            "optional": true
        },
        "Review-Priority": {
            "all": [
                {
                    "value": 0,
                    "_account_id": 1132,
                    "name": "Brian Waldon",
                    "email": "brian@waldon.cc",
                    "username": "bcwaldon"
                },
                {
                    "value": 0,
                    "_account_id": 7,
                    "name": "Jay Pipes",
                    "email": "jaypipes@gmail.com",
                    "username": "jaypipes"
                },
                {
                    "value": 0,
                    "_account_id": 679,
                    "name": "Kevin L. Mitchell",
                    "email": "klmitch@mit.edu",
                    "username": "klmitch"
                },
                {
                    "value": 0,
                    "_account_id": 3,
                    "name": "Jenkins",
                    "username": "jenkins"
                }
            ],
            "values": {
                "-1": "Branch Freeze",
                " 0": "No Priority",
                "+1": "Important Change",
                "+2": "Top Priority / Holds Gate"
            },
            "description": "",
            "default_value": 0,
            "optional": true
        }
    },
    "removable_reviewers": [],
    "reviewers": {
        "REVIEWER": [
            {
                "_account_id": 3,
                "name": "Jenkins",
                "username": "jenkins"
            },
            {
                "_account_id": 7,
                "name": "Jay Pipes",
                "email": "jaypipes@gmail.com",
                "username": "jaypipes"
            },
            {
                "_account_id": 679,
                "name": "Kevin L. Mitchell",
                "email": "klmitch@mit.edu",
                "username": "klmitch"
            },
            {
                "_account_id": 1132,
                "name": "Brian Waldon",
                "email": "brian@waldon.cc",
                "username": "bcwaldon"
            }
        ]
    },
    "pending_reviewers": {},
    "reviewer_updates": [
        {
            "updated": "2011-10-11 16:02:59.000000000",
            "updated_by": {
                "_account_id": 679,
                "name": "Kevin L. Mitchell",
                "email": "klmitch@mit.edu",
                "username": "klmitch"
            },
            "reviewer": {
                "_account_id": 679,
                "name": "Kevin L. Mitchell",
                "email": "klmitch@mit.edu",
                "username": "klmitch"
            },
            "state": "REVIEWER"
        },
        {
            "updated": "2011-10-11 20:16:30.000000000",
            "updated_by": {
                "_account_id": 1132,
                "name": "Brian Waldon",
                "email": "brian@waldon.cc",
                "username": "bcwaldon"
            },
            "reviewer": {
                "_account_id": 1132,
                "name": "Brian Waldon",
                "email": "brian@waldon.cc",
                "username": "bcwaldon"
            },
            "state": "REVIEWER"
        },
        {
            "updated": "2011-10-11 20:18:07.000000000",
            "updated_by": {
                "_account_id": 3,
                "name": "Jenkins",
                "username": "jenkins"
            },
            "reviewer": {
                "_account_id": 3,
                "name": "Jenkins",
                "username": "jenkins"
            },
            "state": "REVIEWER"
        }
    ],
    "messages": [
        {
            "id": "73d3d6bfc50e43e7fedf3bbe4d0b4cd99f143d7e",
            "author": {
                "_account_id": 1132,
                "name": "Brian Waldon",
                "email": "brian@waldon.cc",
                "username": "bcwaldon"
            },
            "real_author": {
                "_account_id": 1132,
                "name": "Brian Waldon",
                "email": "brian@waldon.cc",
                "username": "bcwaldon"
            },
            "date": "2011-10-10 18:04:39.000000000",
            "message": "Patch Set 1: (1 inline comment)\n\n",
            "accounts_in_message": [],
            "_revision_number": 1
        },
        {
            "id": "669e76364f6f2c9b5e0ca27d4ea1ccc55471ecba",
            "author": {
                "_account_id": 7,
                "name": "Jay Pipes",
                "email": "jaypipes@gmail.com",
                "username": "jaypipes"
            },
            "real_author": {
                "_account_id": 7,
                "name": "Jay Pipes",
                "email": "jaypipes@gmail.com",
                "username": "jaypipes"
            },
            "date": "2011-10-10 18:11:58.000000000",
            "message": "Patch Set 1:\n\nI moved it there because it's really only used there... but if it's a big deal, I can move it back.",
            "accounts_in_message": [],
            "_revision_number": 1
        },
        {
            "id": "1845805a49f7cf4404c48e30a145b512009ab2eb",
            "author": {
                "_account_id": 1132,
                "name": "Brian Waldon",
                "email": "brian@waldon.cc",
                "username": "bcwaldon"
            },
            "real_author": {
                "_account_id": 1132,
                "name": "Brian Waldon",
                "email": "brian@waldon.cc",
                "username": "bcwaldon"
            },
            "date": "2011-10-10 18:13:51.000000000",
            "message": "Patch Set 1:\n\nI would prefer to keep all exception classes in the exception module. Sorry!",
            "accounts_in_message": [],
            "_revision_number": 1
        },
        {
            "id": "a6142e124c175c4c455e0508f59ec21f682f0b3b",
            "author": {
                "_account_id": 7,
                "name": "Jay Pipes",
                "email": "jaypipes@gmail.com",
                "username": "jaypipes"
            },
            "real_author": {
                "_account_id": 7,
                "name": "Jay Pipes",
                "email": "jaypipes@gmail.com",
                "username": "jaypipes"
            },
            "date": "2011-10-11 13:21:33.000000000",
            "message": "Uploaded patch set 2.",
            "accounts_in_message": [],
            "_revision_number": 2
        },
        {
            "id": "999b5f32bb461201953ac444702ceeb974b7077e",
            "author": {
                "_account_id": 1132,
                "name": "Brian Waldon",
                "email": "brian@waldon.cc",
                "username": "bcwaldon"
            },
            "real_author": {
                "_account_id": 1132,
                "name": "Brian Waldon",
                "email": "brian@waldon.cc",
                "username": "bcwaldon"
            },
            "date": "2011-10-11 13:22:27.000000000",
            "message": "Patch Set 2: Looks good to me, but someone else must approve\n\nThanks, Jay. Sorry for being picky!",
            "accounts_in_message": [],
            "_revision_number": 2
        },
        {
            "id": "3510ff3c465c583ec4da0c5b4c69addb7b080cdd",
            "author": {
                "_account_id": 679,
                "name": "Kevin L. Mitchell",
                "email": "klmitch@mit.edu",
                "username": "klmitch"
            },
            "real_author": {
                "_account_id": 679,
                "name": "Kevin L. Mitchell",
                "email": "klmitch@mit.edu",
                "username": "klmitch"
            },
            "date": "2011-10-11 15:27:46.000000000",
            "message": "Patch Set 2: (1 inline comment)\n\nI see one PEP8 failure (or at least I believe it's a PEP8 error) that should be fixed; otherwise, looks good!",
            "accounts_in_message": [],
            "_revision_number": 2
        },
        {
            "id": "f70154d7aeb7306b05ca02561770301e282685fa",
            "author": {
                "_account_id": 7,
                "name": "Jay Pipes",
                "email": "jaypipes@gmail.com",
                "username": "jaypipes"
            },
            "real_author": {
                "_account_id": 7,
                "name": "Jay Pipes",
                "email": "jaypipes@gmail.com",
                "username": "jaypipes"
            },
            "date": "2011-10-11 15:54:26.000000000",
            "message": "Uploaded patch set 3.",
            "accounts_in_message": [],
            "_revision_number": 3
        },
        {
            "id": "b82160841b736b209b979261e6505b722128cafd",
            "author": {
                "_account_id": 7,
                "name": "Jay Pipes",
                "email": "jaypipes@gmail.com",
                "username": "jaypipes"
            },
            "real_author": {
                "_account_id": 7,
                "name": "Jay Pipes",
                "email": "jaypipes@gmail.com",
                "username": "jaypipes"
            },
            "date": "2011-10-11 15:54:48.000000000",
            "message": "Patch Set 3:\n\nFixed pep8 errors",
            "accounts_in_message": [],
            "_revision_number": 3
        },
        {
            "id": "a7f304f35dcf9ac4f9a23ffdca06358206c4cea0",
            "author": {
                "_account_id": 679,
                "name": "Kevin L. Mitchell",
                "email": "klmitch@mit.edu",
                "username": "klmitch"
            },
            "real_author": {
                "_account_id": 679,
                "name": "Kevin L. Mitchell",
                "email": "klmitch@mit.edu",
                "username": "klmitch"
            },
            "date": "2011-10-11 16:02:59.000000000",
            "message": "Patch Set 3: Looks good to me, but someone else must approve\n\nLGTM!",
            "accounts_in_message": [],
            "_revision_number": 3
        },
        {
            "id": "5d69342e5d41f55a3aeeef6b9b80968421a2fcd4",
            "author": {
                "_account_id": 1132,
                "name": "Brian Waldon",
                "email": "brian@waldon.cc",
                "username": "bcwaldon"
            },
            "real_author": {
                "_account_id": 1132,
                "name": "Brian Waldon",
                "email": "brian@waldon.cc",
                "username": "bcwaldon"
            },
            "date": "2011-10-11 20:16:30.000000000",
            "message": "Patch Set 3: Looks good to me, approved\n\n",
            "accounts_in_message": [],
            "_revision_number": 3
        },
        {
            "id": "b022abddfcef4e179fd48bf7c0a3d0c00515eaa6",
            "author": {
                "_account_id": 3,
                "name": "Jenkins",
                "username": "jenkins"
            },
            "real_author": {
                "_account_id": 3,
                "name": "Jenkins",
                "username": "jenkins"
            },
            "date": "2011-10-11 20:16:34.000000000",
            "message": "Patch Set 3:\n\nBuild Started https://jenkins.openstack.org/job/glance-merge/101/ (1/3)",
            "accounts_in_message": [],
            "_revision_number": 3
        },
        {
            "id": "678ef06a9961a741a934f1bdb65e67b0dbe1779d",
            "author": {
                "_account_id": 3,
                "name": "Jenkins",
                "username": "jenkins"
            },
            "real_author": {
                "_account_id": 3,
                "name": "Jenkins",
                "username": "jenkins"
            },
            "date": "2011-10-11 20:16:35.000000000",
            "message": "Patch Set 3:\n\nBuild Started https://jenkins.openstack.org/job/glance/89267/ (2/3)",
            "accounts_in_message": [],
            "_revision_number": 3
        },
        {
            "id": "edf5dca1cdb925c1ef815d875c24ba529fe12f7b",
            "author": {
                "_account_id": 3,
                "name": "Jenkins",
                "username": "jenkins"
            },
            "real_author": {
                "_account_id": 3,
                "name": "Jenkins",
                "username": "jenkins"
            },
            "date": "2011-10-11 20:16:38.000000000",
            "message": "Patch Set 3:\n\nBuild Started https://jenkins.openstack.org/job/glance-pep8/274/ (3/3)",
            "accounts_in_message": [],
            "_revision_number": 3
        },
        {
            "id": "700760ac532891f6e69788cf894b18ebeebabce0",
            "author": {
                "_account_id": 3,
                "name": "Jenkins",
                "username": "jenkins"
            },
            "real_author": {
                "_account_id": 3,
                "name": "Jenkins",
                "username": "jenkins"
            },
            "date": "2011-10-11 20:18:07.000000000",
            "message": "Patch Set 3: Verified\n\nBuild Successful \n \nhttps://jenkins.openstack.org/job/glance-merge/101/ : SUCCESS \nhttps://jenkins.openstack.org/job/glance/89267/ : SUCCESS \nhttps://jenkins.openstack.org/job/glance-pep8/274/ : SUCCESS",
            "accounts_in_message": [],
            "_revision_number": 3
        },
        {
            "id": "212085c7153a7254df9fddab6b0cf015612e634c",
            "author": {
                "_account_id": 3,
                "name": "Jenkins",
                "username": "jenkins"
            },
            "real_author": {
                "_account_id": 3,
                "name": "Jenkins",
                "username": "jenkins"
            },
            "date": "2011-10-11 20:18:07.000000000",
            "message": "Change has been successfully merged into the git repository.",
            "accounts_in_message": [],
            "_revision_number": 3
        }
    ],
    "requirements": [],
    "submit_records": []
}